half_subtractor.v
module half_subtractor(output diff , borrow , input a,b);
assign diff=a^b;
assign borrow=(~a)&b;
endmodule

fs_hs.v
module fs_hs(output diff,Bout,input a,b,Bin);
wire w1,w2,w3;
half_subtractor  h1(.a(a),.b(b),.diff(w1),.borrow(w2));

half_subtractor h2(.a(w1),.b(Bin),.diff(diff),.borrow(w3));

or h3(Bout,w2,w3);
endmodule

fs_hs_tb.v
`timescale 1ms/1ms
module fs_hs_tb();
reg a,b,Bin;
wire diff,Bout;
fs_hs h4(.a(a),.b(b),.Bin(Bin),.diff(diff),.Bout(Bout));
initial begin
  $dumpfile("fs_hs_waveform.vcd");
  $dumpvars(0,fs_hs_tb);
  a=0;b=0;Bin=0;#10;
  a=0;b=0;Bin=1;#10;
  a=0;b=1;Bin=0;#10;
  a=0;b=1;Bin=1;#10;
  a=1;b=0;Bin=0;#10;
  a=1;b=0;Bin=1;#10;
  a=1;b=1;Bin=0;#10;
  a=1;b=1;Bin=1;#10;
end
endmodule

fs_hs_waveform.vcd
$date
	Sun Feb 09 23:30:56 2025
$end
$version
	Icarus Verilog
$end
$timescale
	1ms
$end
$scope module fs_hs_tb $end
$var wire 1 ! diff $end
$var wire 1 " Bout $end
$var reg 1 # Bin $end
$var reg 1 $ a $end
$var reg 1 % b $end
$scope module h4 $end
$var wire 1 # Bin $end
$var wire 1 " Bout $end
$var wire 1 $ a $end
$var wire 1 % b $end
$var wire 1 & w3 $end
$var wire 1 ' w2 $end
$var wire 1 ( w1 $end
$var wire 1 ! diff $end
$scope module h1 $end
$var wire 1 $ a $end
$var wire 1 % b $end
$var wire 1 ' borrow $end
$var wire 1 ( diff $end
$upscope $end
$scope module h2 $end
$var wire 1 ( a $end
$var wire 1 # b $end
$var wire 1 & borrow $end
$var wire 1 ! diff $end
$upscope $end
$upscope $end
$upscope $end
$enddefinitions $end
$comment Show the parameter values. $end
$dumpall
$end
#0
$dumpvars
0(
0'
0&
0%
0$
0#
0"
0!
$end
#10
1"
1!
1&
1#
#20
0&
1(
1'
0#
1%
#30
0!
1#
#40
0"
1!
0'
0#
0%
1$
#50
0!
1#
#60
0(
0#
1%
#70
1"
1!
1&
1#
