full_subtractor.v
module full_subtractor(output diff,Bout,input a,b,Bin);
assign diff=a^b^Bin;
assign Bout=((~a)&b)|((~a)&Bin)|(b&Bin);
endmodule

fullSub_tb.v
`timescale 1ms/1ms
module fullSub_tb();
reg a,b,Bin;
wire diff,Bout;
full_subtractor h2(.diff(diff),.Bout(Bout),.a(a),.b(b),.Bin(Bin));
initial begin
  $dumpfile("fullSub_waveform.vcd");
  $dumpvars(0,fullSub_tb);
  
  a=0;b=0;Bin=0;#10;
  a=0;b=0;Bin=1;#10;
  a=0;b=1;Bin=0;#10;
  a=0;b=1;Bin=1;#10;
  a=1;b=0;Bin=0;#10;
  a=1;b=0;Bin=1;#10;
  a=1;b=1;Bin=0;#10;
  a=1;b=1;Bin=1;#10;
end
endmodule

fullSub_waveform.vcd
$date
	Sun Feb 09 23:08:54 2025
$end
$version
	Icarus Verilog
$end
$timescale
	1ms
$end
$scope module fullSub_tb $end
$var wire 1 ! diff $end
$var wire 1 " Bout $end
$var reg 1 # Bin $end
$var reg 1 $ a $end
$var reg 1 % b $end
$scope module h2 $end
$var wire 1 # Bin $end
$var wire 1 " Bout $end
$var wire 1 $ a $end
$var wire 1 % b $end
$var wire 1 ! diff $end
$upscope $end
$upscope $end
$enddefinitions $end
$comment Show the parameter values. $end
$dumpall
$end
#0
$dumpvars
0%
0$
0#
0"
0!
$end
#10
1"
1!
1#
#20
0#
1%
#30
0!
1#
#40
0"
1!
0#
0%
1$
#50
0!
1#
#60
0#
1%
#70
1"
1!
1#
