async_fifo.v
module async_fifo #(
    parameter DATA_WIDTH = 8,  
    parameter DEPTH = 16       
) (
    input wire wr_clk,         
    input wire rd_clk,         
    input wire rst,            
    input wire wr_en,          
    input wire rd_en,          
    input wire [DATA_WIDTH-1:0] din,  
    output reg [DATA_WIDTH-1:0] dout, 
    output reg full,           
    output reg empty           
);
    reg [DATA_WIDTH-1:0] fifo_mem [0:DEPTH-1];  
    reg [$clog2(DEPTH):0] wr_ptr = 0, rd_ptr = 0; 

    always @(posedge wr_clk or posedge rst) begin
        if (rst) begin
            wr_ptr <= 0;
            full <= 0;
        end else if (wr_en && !full) begin
            fifo_mem[wr_ptr] <= din;
            wr_ptr <= wr_ptr + 1;
            if (wr_ptr + 1 == rd_ptr)  
                full <= 1;
            empty <= 0;
        end
    end

    always @(posedge rd_clk or posedge rst) begin
        if (rst) begin
            rd_ptr <= 0;
            empty <= 1;
        end else if (rd_en && !empty) begin
            dout <= fifo_mem[rd_ptr];
            rd_ptr <= rd_ptr + 1;
            if (rd_ptr + 1 == wr_ptr)  
                empty <= 1;
            full <= 0;
        end
    end
endmodule

top_async_fifo.v
module top_async_fifo;
    parameter DATA_WIDTH = 8;
    parameter DEPTH = 16;

    reg wr_clk, rd_clk, rst;   
    reg wr_en, rd_en;          
    reg [DATA_WIDTH-1:0] din;  
    wire [DATA_WIDTH-1:0] dout; 
    wire full, empty;          

    async_fifo #(.DATA_WIDTH(DATA_WIDTH), .DEPTH(DEPTH)) fifo_inst (
        .wr_clk(wr_clk),
        .rd_clk(rd_clk),
        .rst(rst),
        .wr_en(wr_en),
        .rd_en(rd_en),
        .din(din),
        .dout(dout),
        .full(full),
        .empty(empty)
    );

    // Generate Clocks
    always #5 wr_clk = ~wr_clk;  
    always #8 rd_clk = ~rd_clk;  

    // Testbench
    initial begin
        $dumpfile("waveform_fifo.vcd"); // Create VCD file for GTKWave
        $dumpvars(0, top_async_fifo); // Dump all variables

        // Initialize signals
        wr_clk = 0;
        rd_clk = 0;
        rst = 1;
        wr_en = 0;
        rd_en = 0;
        din = 8'h00;

        #20 rst = 0; 

        // Write 4 values to FIFO
        repeat (4) begin
            #10 wr_en = 1; din = din + 1;
        end
        #10 wr_en = 0;

        // Wait before reading
        #50;
        
        // Read 4 values from FIFO
        repeat (4) begin
            #16 rd_en = 1;
        end
        #10 rd_en = 0;

        // End simulation
        #100 $finish;
    end
endmodule

waveform_fifo.vcd
$date
	Mon Mar 03 11:09:19 2025
$end
$version
	Icarus Verilog
$end
$timescale
	1s
$end
$scope module top_async_fifo $end
$var wire 1 ! full $end
$var wire 1 " empty $end
$var wire 8 # dout [7:0] $end
$var parameter 32 $ DATA_WIDTH $end
$var parameter 32 % DEPTH $end
$var reg 8 & din [7:0] $end
$var reg 1 ' rd_clk $end
$var reg 1 ( rd_en $end
$var reg 1 ) rst $end
$var reg 1 * wr_clk $end
$var reg 1 + wr_en $end
$scope module fifo_inst $end
$var wire 8 , din [7:0] $end
$var wire 1 ' rd_clk $end
$var wire 1 ( rd_en $end
$var wire 1 ) rst $end
$var wire 1 * wr_clk $end
$var wire 1 + wr_en $end
$var parameter 32 - DATA_WIDTH $end
$var parameter 32 . DEPTH $end
$var reg 8 / dout [7:0] $end
$var reg 1 " empty $end
$var reg 1 ! full $end
$var reg 5 0 rd_ptr [4:0] $end
$var reg 5 1 wr_ptr [4:0] $end
$upscope $end
$upscope $end
$enddefinitions $end
$comment Show the parameter values. $end
$dumpall
b10000 .
b1000 -
b10000 %
b1000 $
$end
#0
$dumpvars
b0 1
b0 0
bx /
b0 ,
0+
0*
1)
0(
0'
b0 &
bx #
1"
0!
$end
#5
1*
#8
1'
#10
0*
#15
1*
#16
0'
#20
0*
0)
#24
1'
#25
1*
#30
0*
b1 &
b1 ,
1+
#32
0'
#35
0"
b1 1
1*
#40
0*
1'
b10 &
b10 ,
#45
b10 1
1*
#48
0'
#50
0*
b11 &
b11 ,
#55
b11 1
1*
#56
1'
#60
0*
b100 &
b100 ,
#64
0'
#65
b100 1
1*
#70
0*
0+
#72
1'
#75
1*
#80
0*
0'
#85
1*
#88
1'
#90
0*
#95
1*
#96
0'
#100
0*
#104
1'
#105
1*
#110
0*
#112
0'
#115
1*
#120
0*
1'
#125
1*
#128
0'
#130
0*
#135
1*
#136
b1 0
b1 #
b1 /
1'
1(
#140
0*
#144
0'
#145
1*
#150
0*
#152
b10 0
b10 #
b10 /
1'
#155
1*
#160
0*
0'
#165
1*
#168
b11 0
b11 #
b11 /
1'
#170
0*
#175
1*
#176
0'
#180
0*
#184
1"
b100 0
b100 #
b100 /
1'
#185
1*
#190
0*
#192
0'
#194
0(
